mkite_catalysis/settings.py
mkite_catalysis/recipes/__init__.py
mkite_catalysis/recipes/adsorption.py
mkite_catalysis/recipes/base.py
mkite_catalysis/recipes/coverage.py
mkite_catalysis/recipes/supercell.py
mkite_catalysis/recipes/surfgen.py
mkite_catalysis/recipes/tests/__init__.py
mkite_catalysis/recipes/tests/test_adsorption.py
mkite_catalysis/recipes/tests/test_surfgen.py
mkite_catalysis/runners/__init__.py
mkite_catalysis/runners/adsorption.py
mkite_catalysis/runners/coverage.py
mkite_catalysis/runners/deduplicate.py
mkite_catalysis/runners/supercell.py
mkite_catalysis/runners/tests/__init__.py
mkite_catalysis/runners/tests/test_supercell.py
mkite_catalysis/tests/__init__.py
mkite_catalysis/tests/files/__init__.py
mkite_catalysis/tests/files/jobinfo.json
mkite_catalysis/tests/files/jobinfo_surf.json
mkite_catalysis/tests/files/slab.json
mkite_catalysis-24.9.5.dist-info/LICENSE
mkite_catalysis-24.9.5.dist-info/METADATA
mkite_catalysis-24.9.5.dist-info/NOTICE
mkite_catalysis-24.9.5.dist-info/WHEEL
mkite_catalysis-24.9.5.dist-info/entry_points.txt
mkite_catalysis-24.9.5.dist-info/top_level.txt
mkite_catalysis-24.9.5.dist-info/RECORD
