Metadata-Version: 2.1
Name: mkite_catalysis
Version: 24.9.5
Summary: plugin to deal with surface- and catalysis-related operations in mkite
Author-email: Daniel Schwalbe-Koda <dskoda@ucla.edu>
Keywords: workflow,materials-science
Requires-Python: >=3.8
License-File: LICENSE
License-File: NOTICE
Requires-Dist: pydantic >=2.0
Requires-Dist: pymatgen
Requires-Dist: average-minimum-distance ==1.4.1
